ckan_uploader/__init__.py
ckan_uploader/ckan_uploader.py
ckan_uploader/helpers.py
ckan_uploader/models.py
ckan_uploader/test.me.py
ckan_uploader/test.this.py
ckan_uploader/this.funct.py
ckan_uploader-0.1.8.dist-info/DESCRIPTION.rst
ckan_uploader-0.1.8.dist-info/METADATA
ckan_uploader-0.1.8.dist-info/RECORD
ckan_uploader-0.1.8.dist-info/WHEEL
ckan_uploader-0.1.8.dist-info/metadata.json
ckan_uploader-0.1.8.dist-info/top_level.txt
