Metadata-Version: 2.0
Name: ckan-uploader
Version: 0.1.8
Summary: Carga y actualizacion de recursos remotos en una plataforma CKAN 2.5.3+
Home-page: https://github.com/datosgobar/ckan-uploader
Author: Datos Argentina
Author-email: datos@modernizacion.gob.ar
License: ISCL
Keywords: ckan_uploader ckan resources
Platform: UNKNOWN
Classifier: Development Status :: 2 - Pre-Alpha
Classifier: Intended Audience :: Developers
Classifier: License :: OSI Approved :: MIT License
Classifier: Programming Language :: Python :: 2.7
Requires-Dist: arrow (>=0.10.0)
Requires-Dist: ckanapi (>=4.0)
Requires-Dist: httmock (==1.2.6)
Requires-Dist: requests (>=2.13.0)
